Metadata-Version: 1.0
Name: mypytex
Version: 0.3
Summary: Writing latex files and compile it with python and jinja2
Home-page: https://git.opytex.org/lafrite/Pytex
Author: Bertrand Benjamin
Author-email: benjamin.bertrand@opytex.org
License: UNKNOWN
Platform: UNKNOWN
